toxp/__init__.py
toxp/cli.py
toxp/config.py
toxp/exceptions.py
toxp/orchestrator.py
toxp/agents/__init__.py
toxp/agents/coordinator.py
toxp/agents/prompts.py
toxp/agents/reasoning.py
toxp/logging/__init__.py
toxp/logging/session_logger.py
toxp/models/__init__.py
toxp/models/query.py
toxp/models/response.py
toxp/models/result.py
toxp/output/__init__.py
toxp/output/formatter.py
toxp/output/progress.py
toxp/providers/__init__.py
toxp/providers/base.py
toxp/providers/bedrock.py
toxp/providers/registry.py
toxp/utils/__init__.py
toxp/utils/rate_limiter.py
toxp-0.3.0.dist-info/METADATA
toxp-0.3.0.dist-info/WHEEL
toxp-0.3.0.dist-info/entry_points.txt
toxp-0.3.0.dist-info/top_level.txt
toxp-0.3.0.dist-info/RECORD
