Metadata-Version: 2.4
Name: toxp
Version: 0.3.0
Summary: TOXP CLI - Team Of eXPerts parallel reasoning with multiple LLM agents and AWS Bedrock
Author: Team of Experts Contributors
License: MIT
Project-URL: Homepage, https://github.com/team-of-experts/toxp
Project-URL: Documentation, https://github.com/team-of-experts/toxp#readme
Project-URL: Repository, https://github.com/team-of-experts/toxp
Project-URL: Issues, https://github.com/team-of-experts/toxp/issues
Keywords: aws,bedrock,claude,ai,reasoning,parallel-compute,llm,cli
Classifier: Development Status :: 3 - Alpha
Classifier: Intended Audience :: Developers
Classifier: License :: OSI Approved :: MIT License
Classifier: Programming Language :: Python :: 3
Classifier: Programming Language :: Python :: 3.10
Classifier: Programming Language :: Python :: 3.11
Classifier: Programming Language :: Python :: 3.12
Classifier: Programming Language :: Python :: 3.13
Classifier: Environment :: Console
Classifier: Topic :: Scientific/Engineering :: Artificial Intelligence
Requires-Python: >=3.10
Requires-Dist: boto3>=1.35.0
Requires-Dist: pydantic>=2.0.0
Requires-Dist: rich>=13.0.0
Provides-Extra: dev
Requires-Dist: pytest>=8.0.0; extra == "dev"
Requires-Dist: pytest-asyncio>=0.24.0; extra == "dev"
Requires-Dist: hypothesis>=6.100.0; extra == "dev"
Requires-Dist: black>=24.0.0; extra == "dev"
Requires-Dist: mypy>=1.11.0; extra == "dev"
Requires-Dist: ruff>=0.4.0; extra == "dev"
